ADVI/__init__.py
ADVI/__main__.py
ADVI/__version__.py
ADVI/build.py
ADVI/visualize.py
ADVI-0.0.0.dist-info/LICENSE
ADVI-0.0.0.dist-info/METADATA
ADVI-0.0.0.dist-info/WHEEL
ADVI-0.0.0.dist-info/top_level.txt
ADVI-0.0.0.dist-info/RECORD
