Metadata-Version: 2.1
Name: ADVI
Version: 0.0.0
Summary: The handy tool to visualize audio
Home-page: https://github.com/klae01/audio-visualizer
Author: klae01
Author-email: tspt2479@gmail.com
License: MIT
Platform: UNKNOWN
Classifier: Development Status :: 2 - Pre-Alpha
Classifier: License :: OSI Approved :: GNU General Public License v3 (GPLv3)
Classifier: Programming Language :: Python
Classifier: Programming Language :: Python :: 3
Classifier: Programming Language :: Python :: 3.7
Classifier: Programming Language :: Python :: 3.8
Classifier: Programming Language :: Python :: 3.9
Classifier: Programming Language :: Python :: 3.10
Requires-Python: >=3.7.0
License-File: LICENSE
Requires-Dist: av
Requires-Dist: scipy
Requires-Dist: numpy
